flask_defer.py
Flask_Defer-1.1.0.dist-info/DESCRIPTION.rst
Flask_Defer-1.1.0.dist-info/METADATA
Flask_Defer-1.1.0.dist-info/RECORD
Flask_Defer-1.1.0.dist-info/WHEEL
Flask_Defer-1.1.0.dist-info/metadata.json
Flask_Defer-1.1.0.dist-info/top_level.txt
