Metadata-Version: 2.0
Name: Flask-Defer
Version: 1.1.0
Summary: Flask extension to defer task execution under after request teardown
Home-page: https://github.com/brettlangdon/flask-defer.git
Author: Brett Langdon
Author-email: me@brett.is
License: MIT
Platform: any
Classifier: Environment :: Web Environment
Classifier: Intended Audience :: Developers
Classifier: License :: OSI Approved :: MIT License
Classifier: Operating System :: OS Independent
Classifier: Programming Language :: Python
Classifier: Topic :: Internet :: WWW/HTTP :: Dynamic Content
Classifier: Topic :: Software Development :: Libraries :: Python Modules
Requires-Dist: Flask
